{
  "$schema": "http://json-schema.org/draft-07/schema#",
  "title": "Datasets",
  "type": "object",
  "properties": {
    "datasets": {
      "type": "array",
      "items": {
        "type": "object",
        "properties": {
          "name": { "type": "string", "minLength": 1 },
          "url": { "type": "string", "format": "uri" },
          "description": { "type": "string", "minLength": 1 },
          "license": { "type": ["string", "null"] },
          "provider": { "type": ["string", "null"] },
          "domain": { "type": ["string", "null"] },
          "modality": { "type": ["string", "null"] },
          "spatial_resolution": { "type": ["string", "null"] },
          "temporal_resolution": { "type": ["string", "null"] },
          "coverage": { "type": ["string", "null"] },
          "tasks_supported": { "type": ["array", "null"], "items": { "type": "string" } },
          "access": { "type": ["string", "null"] },
          "citation": { "type": ["string", "null"] }
        },
        "required": ["name", "url", "description"],
        "additionalProperties": true
      }
    }
  },
  "required": ["datasets"],
  "additionalProperties": false
}
